MANIFEST.in
requirements.txt
setup.cfg
setup.py
test_requirements.txt
eth_interface/__init__.py
eth_interface/eip165.py
eth_interface.egg-info/PKG-INFO
eth_interface.egg-info/SOURCES.txt
eth_interface.egg-info/dependency_links.txt
eth_interface.egg-info/requires.txt
eth_interface.egg-info/top_level.txt
eth_interface/unittest/__init__.py
eth_interface/unittest/base.py
tests/test_eip165.py